<?xml version="1.0" encoding="iso-8859-1"?>
<root version="3.3" release="8|CoreRPG:4">
	<character>
		<abilities>
			<charisma>
				<bonus type="number">0</bonus>
				<save type="number">0</save>
				<savemodifier type="number">0</savemodifier>
				<saveprof type="number">0</saveprof>
				<score type="number">10</score>
			</charisma>
			<constitution>
				<bonus type="number">2</bonus>
				<save type="number">4</save>
				<savemodifier type="number">0</savemodifier>
				<saveprof type="number">1</saveprof>
				<score type="number">15</score>
			</constitution>
			<dexterity>
				<bonus type="number">0</bonus>
				<save type="number">0</save>
				<savemodifier type="number">0</savemodifier>
				<saveprof type="number">0</saveprof>
				<score type="number">10</score>
			</dexterity>
			<intelligence>
				<bonus type="number">1</bonus>
				<save type="number">1</save>
				<savemodifier type="number">0</savemodifier>
				<saveprof type="number">0</saveprof>
				<score type="number">12</score>
			</intelligence>
			<strength>
				<bonus type="number">3</bonus>
				<save type="number">5</save>
				<savemodifier type="number">0</savemodifier>
				<saveprof type="number">1</saveprof>
				<score type="number">17</score>
			</strength>
			<wisdom>
				<bonus type="number">0</bonus>
				<save type="number">0</save>
				<savemodifier type="number">0</savemodifier>
				<saveprof type="number">0</saveprof>
				<score type="number">10</score>
			</wisdom>
		</abilities>
		<adventurelist>
		</adventurelist>
		<age type="string">52</age>
		<alignment type="string">NG</alignment>
		<background type="string">Teacher</background>
		<backgroundlink type="windowreference">
			<class>reference_background</class>
			<recordname>background.id-00039@Incarnate-5eExpansion</recordname>
		</backgroundlink>
		<bonds type="string">Everything I do is for the common people.\nI would still lay down my life for the people I served with.</bonds>
		<classes>
			<id-00001>
				<hddie type="dice">d10</hddie>
				<hdused type="number">0</hdused>
				<level type="number">3</level>
				<name type="string">Fighter</name>
				<shortcut type="windowreference">
					<class>reference_class</class>
					<recordname>class.profighter@Incarnate-5eExpansion</recordname>
				</shortcut>
			</id-00001>
		</classes>
		<coins>
			<slot1>
				<amount type="number">253</amount>
				<name type="string">GP</name>
			</slot1>
			<slot2>
				<amount type="number">0</amount>
				<name type="string">PP</name>
			</slot2>
			<slot3>
				<amount type="number">47</amount>
				<name type="string">CP</name>
			</slot3>
			<slot4>
				<amount type="number">0</amount>
				<name type="string">EP</name>
			</slot4>
			<slot5>
				<amount type="number">44</amount>
				<name type="string">SP</name>
			</slot5>
			<slot6>
				<amount type="number">0</amount>
			</slot6>
		</coins>
		<defenses>
			<ac>
				<armor type="number">6</armor>
				<dexbonus type="string">no</dexbonus>
				<disstealth type="number">1</disstealth>
				<misc type="number">0</misc>
				<prof type="number">1</prof>
				<shield type="number">2</shield>
				<temporary type="number">0</temporary>
				<total type="number">18</total>
			</ac>
		</defenses>
		<encumbrance>
			<encumbered type="number">85</encumbered>
			<encumberedheavy type="number">170</encumberedheavy>
			<liftpushdrag type="number">510</liftpushdrag>
			<load type="number">109.7</load>
			<max type="number">255</max>
		</encumbrance>
		<exp type="number">56</exp>
		<expneeded type="number">0</expneeded>
		<featlist>
		</featlist>
		<featurelist>
			<id-00002>
				<locked type="number">1</locked>
				<name type="string">Attentive Teacher</name>
				<source type="string">Teacher</source>
				<text type="formattedtext">
					<p>We all learn better when people pay attention to us and help us. As a teacher you learned to pay attention to your students. When you study someone while they are performing a task you get an impression of how well they are doing.</p>
					<p>(GMs this is meant to give a hint at how ability checks in the die tower are going. This may let a studying teacher figure out someone is struggling and help the player decide if they rolled a 1 and were fed a crazy response or if they really have found something cool.)</p>
				</text>
			</id-00002>
			<id-00003>
				<level type="number">1</level>
				<locked type="number">1</locked>
				<name type="string">Fighting Style</name>
				<source type="string">Fighter</source>
				<specializationchoice type="number">0</specializationchoice>
				<text type="formattedtext">
					<p>You adopt a particular style of fighting as your specialty. Choose one of the following options. You can't take a Fighting Style option more than once, even if you later get to choose again.</p>
					<p><b>Archery</b></p>
					<p>You gain a +2 bonus to attack rolls you make with ranged weapons.</p>
					<linklist>
						<link class="power" recordname="spell.fightingstylearchery@Incarnate-5eExpansion">Fighting Style - Archery</link>
					</linklist>
					<p><b>Defense</b></p>
					<p>While you are wearing armor, you gain a +1 bonus to AC.</p>
					<linklist>
						<link class="power" recordname="spell.fightingstyledefense@Incarnate-5eExpansion">Fighting Style - Defense</link>
					</linklist>
					<p><b>Dueling</b></p>
					<p>When you are wielding a melee weapon in one hand and no other weapons, you gain a +2 bonus to damage rolls with that weapon.</p>
					<linklist>
						<link class="power" recordname="spell.fightingstyledueling@Incarnate-5eExpansion">Fighting Style - Dueling</link>
					</linklist>
					<p><b>Great Weapon Fighting</b></p>
					<p>When you roll a 1 or 2 on a damage die for an attack you make with a melee weapon that you are wielding with two hands, you can re-roll the die and must use the new roll, even if the new roll is a 1 or a 2. The weapon must have the two-handed or versatile property for you to gain this benefit.</p>
					<p><b>Protection</b></p>
					<p>When a creature you can see attacks a target other than you that is within 5 feet of you, you can use your reaction to impose disadvantage on the attack roll. You must be wielding a shield.</p>
					<linklist>
						<link class="power" recordname="spell.fightingstyleprotection@Incarnate-5eExpansion">Fighting Style - Protection</link>
					</linklist>
					<p><b>Two-Weapon Fighting</b></p>
					<p>When you engage in two-weapon fighting, you can add your ability modifier to the damage of the second attack.</p>
				</text>
			</id-00003>
			<id-00004>
				<level type="number">1</level>
				<locked type="number">1</locked>
				<name type="string">Second Wind</name>
				<source type="string">Fighter</source>
				<specializationchoice type="number">0</specializationchoice>
				<text type="formattedtext">
					<h>Action Coding</h>
					<linklist>
						<link class="power" recordname="spell.secondwind@Incarnate-5eExpansion">Second Wind</link>
					</linklist>
					<h>Description</h>
					<p>You have a limited well of stamina that you can draw on to protect yourself from harm. On your turn, you can use a bonus action to regain hit points equal to 1d10 + your fighter level. Once you use this feature, you must finish a short or long rest before you can use it again.</p>
				</text>
			</id-00004>
			<id-00006>
				<level type="number">2</level>
				<locked type="number">1</locked>
				<name type="string">Action Surge</name>
				<source type="string">Fighter</source>
				<specializationchoice type="number">0</specializationchoice>
				<text type="formattedtext">
					<p>Starting at 2nd level, you can push yourself beyond your normal limits for a moment. On your turn, you can take one additional action on top of your regular action and a possible bonus action.</p>
					<p>Once you use this feature, you must finish a short or long rest before you can use it again. Starting at 17th level, you can use it twice before a rest, but only once on the same turn.</p>
				</text>
			</id-00006>
			<id-00007>
				<locked type="number">1</locked>
				<name type="string">Dragon Slayer</name>
				<source type="string">Fighter</source>
				<text type="formattedtext">
					<p>The crackling of lightning through the sky gives you a brief glimpse of wings flapping as the dragon turns for another pass. You ready your spear and just as it is about to open its great maw to breath another blast of doom your pitch your spear forward down its throat.</p>
					<p>Dragon slaying is not for the light hearted, but for those bold, and possibly stupid enough to seek the profession they will find great appreciation from those they save.</p>
					<h>Abilities</h>
					<linklist>
						<link class="reference_classfeature" recordname="class.profighter.features.id-00039@Incarnate-5eExpansion">Level 3: Dragonslayer's Spear</link>
						<link class="reference_classfeature" recordname="class.profighter.features.id-00040@Incarnate-5eExpansion">Level 7: Electrified Charge</link>
						<link class="reference_classfeature" recordname="class.profighter.features.id-00041@Incarnate-5eExpansion">Level 10: Dragonslayer's Lightning</link>
						<link class="reference_classfeature" recordname="class.profighter.features.id-00042@Incarnate-5eExpansion">Level 15: Electrified</link>
						<link class="reference_classfeature" recordname="class.profighter.features.id-00043@Incarnate-5eExpansion">Level 18: Dragonslayer's Lightning</link>
					</linklist>
					<h>Copy Left Notice</h>
					<p>This content was inspired by a source under the GNU Public Use License. The original content is copy left and can be found</p>
					<linklist>
						<link class="referencemanualpage" recordname="referencemanual4.DandDwiki_PRO_00051@Incarnate-5eExpansion">here</link>
					</linklist>
					<p>All modifications are protected and all rights are reserved to the greatest extent permissible by law.</p>
				</text>
			</id-00007>
			<id-00008>
				<level type="number">3</level>
				<locked type="number">1</locked>
				<name type="string">Dragonslayer's Spear</name>
				<source type="string">Fighter</source>
				<specialization type="string">Dragon Slayer</specialization>
				<specializationchoice type="number">0</specializationchoice>
				<text type="formattedtext">
					<h>Item Coding</h>
					<linklist>
						<link class="item" recordname="item.id-00359@Incarnate-5eExpansion">Dragonslayer's Spear</link>
					</linklist>
					<h>Description</h>
					<p>At 3rd Level, whenever you touch a spear it becomes a Dragonslayer Spear. A spear will only remain a Dragonslayer Spear for 1 round after leaving your hand.</p>
					<p>You will use a Dragonslayer's Spear to perform the following abilities at higher levels:</p>
					<linklist>
						<link class="reference_classfeature" recordname="class.profighter.features.id-00040@Incarnate-5eExpansion">Level 7: Electrified Charge</link>
						<link class="reference_classfeature" recordname="class.profighter.features.id-00041@Incarnate-5eExpansion">Level 10: Dragonslayer's Lightning</link>
						<link class="reference_classfeature" recordname="class.profighter.features.id-00042@Incarnate-5eExpansion">Level 15: Electrified</link>
						<link class="reference_classfeature" recordname="class.profighter.features.id-00043@Incarnate-5eExpansion">Level 18: Dragonslayer's Lightning</link>
					</linklist>
				</text>
			</id-00008>
		</featurelist>
		<flaws type="string">I never forget an insult, and I bide my time for revenge.</flaws>
		<gender type="string">Male</gender>
		<height type="string">5'6&#34;</height>
		<hp>
			<deathsavefail type="number">0</deathsavefail>
			<deathsavesuccess type="number">0</deathsavesuccess>
			<temporary type="number">0</temporary>
			<total type="number">28</total>
			<wounds type="number">17</wounds>
		</hp>
		<ideals type="string">I always try to help those in need, no matter what the personal cost.\nOur lot is to lay down our lives in defense of others.</ideals>
		<initiative>
			<misc type="number">0</misc>
			<temporary type="number">0</temporary>
			<total type="number">0</total>
		</initiative>
		<inventorylist>
			<id-00001>
				<carried type="number">1</carried>
				<cost type="string">10 GP</cost>
				<count type="number">1</count>
				<isidentified type="number">1</isidentified>
				<locked type="number">1</locked>
				<name type="string">Ink (1-ounce Bottle)</name>
				<subtype type="string">Standard</subtype>
				<type type="string">Adventuring Gear</type>
				<weight type="number">0.06</weight>
			</id-00001>
			<id-00002>
				<carried type="number">1</carried>
				<cost type="string">2 CP</cost>
				<count type="number">1</count>
				<isidentified type="number">1</isidentified>
				<locked type="number">1</locked>
				<name type="string">Ink Pen</name>
				<subtype type="string">Standard</subtype>
				<type type="string">Adventuring Gear</type>
				<weight type="number">0.02</weight>
			</id-00002>
			<id-00003>
				<ac type="number">0</ac>
				<bonus type="number">0</bonus>
				<carried type="number">1</carried>
				<cost type="string">5 SP</cost>
				<count type="number">1</count>
				<description type="formattedtext">
					<p></p>
				</description>
				<isidentified type="number">1</isidentified>
				<locked type="number">1</locked>
				<name type="string">Clothes, Common</name>
				<subtype type="string">Standard</subtype>
				<type type="string">Adventuring Gear</type>
				<weight type="number">3</weight>
			</id-00003>
			<id-00004>
				<ac type="number">0</ac>
				<bonus type="number">0</bonus>
				<carried type="number">1</carried>
				<cost type="string">1 CP</cost>
				<count type="number">1</count>
				<description type="formattedtext">
					<p>This tiny leather pouch is perfect for keeping your coins close at hand. Just watch out for someone trying to cut it off of your belt.</p>
				</description>
				<isidentified type="number">1</isidentified>
				<locked type="number">1</locked>
				<name type="string">Coin Pouch - Small</name>
				<rarity type="string">Common</rarity>
				<subtype type="string">Standard</subtype>
				<type type="string">Adventuring Gear</type>
				<weight type="number">0.1</weight>
			</id-00004>
			<id-00005>
				<carried type="number">1</carried>
				<cost type="string">1 SP</cost>
				<count type="number">1</count>
				<isidentified type="number">1</isidentified>
				<locked type="number">1</locked>
				<name type="string">Parchment (One Sheet)</name>
				<subtype type="string">Standard</subtype>
				<type type="string">Adventuring Gear</type>
				<weight type="number">0.02</weight>
			</id-00005>
			<id-00006>
				<ac type="number">0</ac>
				<bonus type="number">0</bonus>
				<carried type="number">1</carried>
				<cost type="string">5 GP</cost>
				<count type="number">1</count>
				<description type="formattedtext">
					<p>This book covers something significant from history, this may range from a war, plague, or even the chronicles of a king.</p>
				</description>
				<isidentified type="number">1</isidentified>
				<locked type="number">1</locked>
				<name type="string">Book, Historical</name>
				<rarity type="string">Very Rare</rarity>
				<subtype type="string">Standard</subtype>
				<type type="string">Adventuring Gear</type>
				<weight type="number">1</weight>
			</id-00006>
			<id-00007>
				<ac type="number">16</ac>
				<bonus type="number">0</bonus>
				<carried type="number">2</carried>
				<cost type="string">75 GP</cost>
				<count type="number">1</count>
				<description type="formattedtext">
					<p>Made of interlocking metal rings, chain mail includes a layer of quilted fabric worn underneath the mail to prevent chafing and to cushion the impact of blows. The suit includes gauntlets.</p>
				</description>
				<dexbonus type="string">-</dexbonus>
				<isidentified type="number">1</isidentified>
				<istemplate type="number">0</istemplate>
				<locked type="number">1</locked>
				<name type="string">Chain Mail Armor</name>
				<nonid_name type="string">Chain Mail</nonid_name>
				<nonidentified type="string">Some well-crafted chain mail armor.</nonidentified>
				<stealth type="string">Disadvantage</stealth>
				<strength type="string">Str 13</strength>
				<subtype type="string">Heavy Armor</subtype>
				<type type="string">Armor</type>
				<weight type="number">55</weight>
			</id-00007>
			<id-00008>
				<ac type="number">0</ac>
				<bonus type="number">2</bonus>
				<carried type="number">2</carried>
				<cost type="string">10 GP</cost>
				<count type="number">1</count>
				<description type="formattedtext">
					<p>-</p>
				</description>
				<dexbonus type="string">-</dexbonus>
				<isidentified type="number">1</isidentified>
				<locked type="number">1</locked>
				<name type="string">Shield</name>
				<nonid_name type="string">Shield</nonid_name>
				<nonidentified type="string">A well crafted shield.</nonidentified>
				<stealth type="string">-</stealth>
				<strength type="string">-</strength>
				<subtype type="string">Shield</subtype>
				<type type="string">Armor</type>
				<weight type="number">6</weight>
			</id-00008>
			<id-00010>
				<ac type="number">0</ac>
				<bonus type="number">0</bonus>
				<carried type="number">2</carried>
				<cost type="string">5 GP</cost>
				<count type="number">2</count>
				<damage type="string">1d6 slashing</damage>
				<description type="formattedtext">
					<p>-</p>
				</description>
				<isidentified type="number">1</isidentified>
				<istemplate type="number">0</istemplate>
				<locked type="number">1</locked>
				<name type="string">Handaxe</name>
				<nonid_name type="string">Handaxe</nonid_name>
				<nonidentified type="string">A sharp stout handaxe.</nonidentified>
				<properties type="string">Light, thrown (range 20/60)</properties>
				<subtype type="string">Simple Melee Weapons</subtype>
				<type type="string">Weapon</type>
				<weight type="number">2</weight>
			</id-00010>
			<id-00011>
				<carried type="number">1</carried>
				<cost type="string">1 GP</cost>
				<count type="number">1</count>
				<isidentified type="number">1</isidentified>
				<locked type="number">1</locked>
				<name type="string">Rope, Hempen (50 Feet)</name>
				<subtype type="string">Standard</subtype>
				<type type="string">Adventuring Gear</type>
				<weight type="number">10</weight>
			</id-00011>
			<id-00012>
				<carried type="number">1</carried>
				<cost type="string">1 GP</cost>
				<count type="number">1</count>
				<description type="formattedtext">
					<p></p>
				</description>
				<isidentified type="number">1</isidentified>
				<locked type="number">1</locked>
				<name type="string">Bedroll</name>
				<subtype type="string">Standard</subtype>
				<type type="string">Adventuring Gear</type>
				<weight type="number">7</weight>
			</id-00012>
			<id-00013>
				<carried type="number">1</carried>
				<cost type="string">2 SP</cost>
				<count type="number">1</count>
				<isidentified type="number">1</isidentified>
				<locked type="number">1</locked>
				<name type="string">Waterskin</name>
				<subtype type="string">Standard</subtype>
				<type type="string">Adventuring Gear</type>
				<weight type="number">5</weight>
			</id-00013>
			<id-00014>
				<ac type="number">0</ac>
				<bonus type="number">0</bonus>
				<carried type="number">1</carried>
				<cost type="string">2 GP</cost>
				<count type="number">1</count>
				<description type="formattedtext">
					<p></p>
				</description>
				<isidentified type="number">1</isidentified>
				<locked type="number">1</locked>
				<name type="string">Backpack</name>
				<subtype type="string">Standard</subtype>
				<type type="string">Adventuring Gear</type>
				<weight type="number">5</weight>
			</id-00014>
			<id-00015>
				<carried type="number">1</carried>
				<cost type="string">1 CP</cost>
				<count type="number">1</count>
				<description type="formattedtext">
					<p>A torch burns for 1 hour, providing bright light in a 20-foot radius and dim light for an additional 20 feet. If you make a melee attack with a burning torch and hit, it deals 1 fire damage.</p>
				</description>
				<isidentified type="number">1</isidentified>
				<locked type="number">1</locked>
				<name type="string">Torch</name>
				<subtype type="string">Standard</subtype>
				<type type="string">Adventuring Gear</type>
				<weight type="number">1</weight>
			</id-00015>
			<id-00016>
				<ac type="number">0</ac>
				<bonus type="number">0</bonus>
				<carried type="number">1</carried>
				<cost type="string">5 SP</cost>
				<count type="number">1</count>
				<description type="formattedtext">
					<p>Rations consist of dry foods suitable for extended travel, including jerky, dried fruit, hardtack, and nuts.</p>
				</description>
				<isidentified type="number">1</isidentified>
				<locked type="number">1</locked>
				<name type="string">Rations (1 Day)</name>
				<subtype type="string">Standard</subtype>
				<type type="string">Adventuring Gear</type>
				<weight type="number">2</weight>
			</id-00016>
			<id-00017>
				<carried type="number">1</carried>
				<cost type="string">2 SP</cost>
				<count type="number">1</count>
				<description type="formattedtext">
					<p>This tin box contains a cup and simple cutlery. The box clamps together, and one side can be used as a cooking pan and the other as a plate or shallow bowl.</p>
				</description>
				<isidentified type="number">1</isidentified>
				<locked type="number">1</locked>
				<name type="string">Mess Kit</name>
				<subtype type="string">Equipment Kits</subtype>
				<type type="string">Adventuring Gear</type>
				<weight type="number">1</weight>
			</id-00017>
			<id-00018>
				<carried type="number">1</carried>
				<cost type="string">5 SP</cost>
				<count type="number">1</count>
				<description type="formattedtext">
					<p>This small container holds flint, fire steel, and tinder (usually dry cloth soaked in light oil) used to kindle a fire. Using it to light a torch-or anything else with abundant, exposed fuel-takes an action. Lighting any other fire takes 1 minute.</p>
				</description>
				<isidentified type="number">1</isidentified>
				<locked type="number">1</locked>
				<name type="string">Tinderbox</name>
				<subtype type="string">Standard</subtype>
				<type type="string">Adventuring Gear</type>
				<weight type="number">1</weight>
			</id-00018>
			<id-00019>
				<ac type="number">0</ac>
				<bonus type="number">0</bonus>
				<carried type="number">2</carried>
				<cost type="string">5 GP</cost>
				<count type="number">2</count>
				<damage type="string">1d4 piercing 1d4 lightning</damage>
				<description type="formattedtext">
					<h>Action Coding</h>
					<linklist>
						<link class="power" recordname="spell.dragonslayersspear@Incarnate-5eExpansion">Dragonslayer's Spear</link>
					</linklist>
					<h>Description</h>
					<p>This heavy duty spear seems to be charged with a mystical lightning energy which discharges on impact.</p>
					<p>On a hit, the target cannot take any reactions until the start of its next turn.</p>
					<h>Link to Class Feature</h>
					<linklist>
						<link class="reference_classfeature" recordname="class.profighter.features.id-00039@Incarnate-5eExpansion">Dragonslayer's Spear</link>
					</linklist>
				</description>
				<isidentified type="number">1</isidentified>
				<istemplate type="number">0</istemplate>
				<locked type="number">1</locked>
				<name type="string">Dragonslayer's Spear</name>
				<nonid_name type="string">Dragonslayer's Spear</nonid_name>
				<nonidentified type="string">This heavy duty spear seems to be charged with a mystical energy.\n(Please ask your GM to identify this item for you. Some of it is hidden due to the way FG is programmed to keep it from showing up in the general items section.)</nonidentified>
				<properties type="string">Thrown (range 20/60), versatile (1d8)</properties>
				<rarity type="string">(requires attunement by a Dragonslayer fighter)</rarity>
				<subtype type="string">Simple Melee Weapons</subtype>
				<type type="string">Weapon</type>
				<weight type="number">4</weight>
			</id-00019>
			<id-00020>
				<carried type="number">1</carried>
				<count type="number">1</count>
				<locked type="number">1</locked>
				<name type="string">heartstone</name>
				<weight type="number">0</weight>
			</id-00020>
			<id-00021>
				<ac type="number">0</ac>
				<bonus type="number">0</bonus>
				<carried type="number">1</carried>
				<cost type="string">100 GP</cost>
				<count type="number">1</count>
				<description type="formattedtext">
					<h>Action Coding</h>
					<linklist>
						<link class="power" recordname="spell.potionofgreaterhealing@Incarnate-5eExpansion">Potion of Greater Healing</link>
					</linklist>
					<h>Description</h>
					<p>You regain hit points when you drink this potion.</p>
					<p>The number of hit points depends on the potion's rarity, as shown in the Potions of Healing table. Whatever its potency, the potion's red liquid glimmers when agitated.</p>
					<h>Potions of Healing</h>
					<table>
						<tr>
							<td>Potion of .</td>
							<td>Rarity</td>
							<td>HP Regained</td>
						</tr>
						<tr>
							<td>Greater healing</td>
							<td>Uncommon</td>
							<td>4d4 + 4</td>
						</tr>
					</table>
				</description>
				<isidentified type="number">1</isidentified>
				<locked type="number">1</locked>
				<name type="string">Greater Potion of Healing</name>
				<nonid_name type="string">Dim Potion</nonid_name>
				<nonidentified type="string">The potion's red liquid glimmers when agitated.</nonidentified>
				<rarity type="string">Uncommon</rarity>
				<type type="string">Potion</type>
				<weight type="number">0.5</weight>
			</id-00021>
		</inventorylist>
		<languagelist>
			<id-00001>
				<name type="string">Common </name>
			</id-00001>
			<id-00002>
				<name type="string">Draconic</name>
			</id-00002>
			<id-00003>
				<name type="string">Dwarvish</name>
			</id-00003>
			<id-00004>
				<name type="string">Elvish</name>
			</id-00004>
		</languagelist>
		<level type="number">3</level>
		<name type="string">Vok</name>
		<perception type="number">10</perception>
		<perceptionmodifier type="number">0</perceptionmodifier>
		<personalitytraits type="string">When work needs doing, I do the work.\nI talk down to others when speaking on a field I believe myself to be knowledgeable in.</personalitytraits>
		<powergroup>
			<id-00001>
				<atkprof type="number">1</atkprof>
				<castertype type="string">memorization</castertype>
				<name type="string">Class</name>
				<saveprof type="number">1</saveprof>
			</id-00001>
		</powergroup>
		<powermeta>
			<pactmagicslots1>
				<max type="number">0</max>
				<used type="number">0</used>
			</pactmagicslots1>
			<pactmagicslots2>
				<max type="number">0</max>
				<used type="number">0</used>
			</pactmagicslots2>
			<pactmagicslots3>
				<max type="number">0</max>
				<used type="number">0</used>
			</pactmagicslots3>
			<pactmagicslots4>
				<max type="number">0</max>
				<used type="number">0</used>
			</pactmagicslots4>
			<pactmagicslots5>
				<max type="number">0</max>
				<used type="number">0</used>
			</pactmagicslots5>
			<pactmagicslots6>
				<max type="number">0</max>
				<used type="number">0</used>
			</pactmagicslots6>
			<pactmagicslots7>
				<max type="number">0</max>
				<used type="number">0</used>
			</pactmagicslots7>
			<pactmagicslots8>
				<max type="number">0</max>
				<used type="number">0</used>
			</pactmagicslots8>
			<pactmagicslots9>
				<max type="number">0</max>
				<used type="number">0</used>
			</pactmagicslots9>
			<spellslots1>
				<max type="number">0</max>
				<used type="number">0</used>
			</spellslots1>
			<spellslots2>
				<max type="number">0</max>
				<used type="number">0</used>
			</spellslots2>
			<spellslots3>
				<max type="number">0</max>
				<used type="number">0</used>
			</spellslots3>
			<spellslots4>
				<max type="number">0</max>
				<used type="number">0</used>
			</spellslots4>
			<spellslots5>
				<max type="number">0</max>
				<used type="number">0</used>
			</spellslots5>
			<spellslots6>
				<max type="number">0</max>
				<used type="number">0</used>
			</spellslots6>
			<spellslots7>
				<max type="number">0</max>
				<used type="number">0</used>
			</spellslots7>
			<spellslots8>
				<max type="number">0</max>
				<used type="number">0</used>
			</spellslots8>
			<spellslots9>
				<max type="number">0</max>
				<used type="number">0</used>
			</spellslots9>
		</powermeta>
		<powermode type="string">combat</powermode>
		<powers>
			<id-00001>
				<actions>
					<id-00001>
						<durmod type="number">1</durmod>
						<label type="string">Dragonslayer's Spear; NOTE: cannot take a reaction until start of its turn</label>
						<order type="number">1</order>
						<type type="string">effect</type>
					</id-00001>
				</actions>
				<cast type="number">0</cast>
				<description type="formattedtext">
					<p></p>
				</description>
				<group type="string">Class</group>
				<level type="number">0</level>
				<locked type="number">1</locked>
				<name type="string">Dragonslayer's Spear</name>
				<prepared type="number">0</prepared>
				<ritual type="number">0</ritual>
			</id-00001>
			<id-00002>
				<actions>
					<id-00001>
						<heallist>
							<id-00001>
								<bonus type="number">0</bonus>
								<dice type="dice">d10</dice>
								<stat type="string">fighter</stat>
							</id-00001>
						</heallist>
						<healtargeting type="string">self</healtargeting>
						<order type="number">1</order>
						<type type="string">heal</type>
					</id-00001>
				</actions>
				<cast type="number">0</cast>
				<description type="formattedtext">
					<linklist>
						<link class="reference_classfeature" recordname="class.profighter.features.id-00035@Incarnate-5eExpansion">Second Wind</link>
					</linklist>
				</description>
				<group type="string">Class</group>
				<level type="number">0</level>
				<locked type="number">1</locked>
				<name type="string">Second Wind</name>
				<prepared type="number">1</prepared>
				<ritual type="number">0</ritual>
				<usesperiod type="string">enc</usesperiod>
			</id-00002>
			<id-00003>
				<actions>
					<id-00001>
						<durmod type="number">1</durmod>
						<durunit type="string">day</durunit>
						<label type="string">Fighting Style Defense; AC:1</label>
						<order type="number">1</order>
						<targeting type="string">self</targeting>
						<type type="string">effect</type>
					</id-00001>
				</actions>
				<cast type="number">0</cast>
				<description type="formattedtext">
					<linklist>
						<link class="reference_classfeature" recordname="class.proranger.features.id-00055@Incarnate-5eExpansion">Fighting Style</link>
					</linklist>
				</description>
				<group type="string">Class</group>
				<level type="number">0</level>
				<locked type="number">1</locked>
				<name type="string">Fighting Style - Defense</name>
				<prepared type="number">0</prepared>
				<ritual type="number">0</ritual>
			</id-00003>
			<id-00004>
				<actions>
					<id-00001>
						<durmod type="number">1</durmod>
						<durunit type="string">day</durunit>
						<label type="string">RESIST: lightning</label>
						<order type="number">1</order>
						<targeting type="string">self</targeting>
						<type type="string">effect</type>
					</id-00001>
				</actions>
				<cast type="number">0</cast>
				<description type="formattedtext">
					<p></p>
				</description>
				<group type="string">Class</group>
				<level type="number">0</level>
				<locked type="number">1</locked>
				<name type="string">Type Resistance (Lightning)</name>
				<prepared type="number">0</prepared>
				<ritual type="number">0</ritual>
			</id-00004>
			<id-00005>
				<actions>
					<id-00001>
						<atkmod type="number">0</atkmod>
						<atkprof type="number">1</atkprof>
						<onmissdamage type="string">half</onmissdamage>
						<order type="number">1</order>
						<savedcbase type="string">ability</savedcbase>
						<savedcmod type="number">0</savedcmod>
						<savedcprof type="number">1</savedcprof>
						<savedcstat type="string">constitution</savedcstat>
						<savemagic type="number">0</savemagic>
						<savetype type="string">dexterity</savetype>
						<type type="string">cast</type>
					</id-00001>
					<id-00002>
						<damagelist>
							<id-00001>
								<bonus type="number">0</bonus>
								<dice type="dice">d6,d6</dice>
								<type type="string">lightning</type>
							</id-00001>
						</damagelist>
						<order type="number">2</order>
						<type type="string">damage</type>
					</id-00002>
				</actions>
				<cast type="number">0</cast>
				<description type="formattedtext">
					<linklist>
						<link class="power" recordname="..">Draconic Ancestry</link>
					</linklist>
					<p>You can use your action to exhale destructive energy. Your draconic ancestry determines the size, shape, and damage type of the exhalation.</p>
					<p>When you use your breath weapon, each creature in the area of the exhalation must make a saving throw, the type of which is determined by your draconic ancestry. The DC for this saving throw equals 8 + your Constitution modifier + your proficiency bonus. A creature takes 2d6 damage on a failed save, and half as much damage on a successful one. The damage increases to 3d6 at 6th level, 4d6 at 11th level, and 5d6 at 16th level.</p>
					<p>After you use your breath weapon, you can't use it again until you complete a short or long rest.</p>
				</description>
				<group type="string">Class</group>
				<level type="number">0</level>
				<locked type="number">1</locked>
				<name type="string">Breath Weapon (Lightning)</name>
				<prepared type="number">0</prepared>
				<ritual type="number">0</ritual>
			</id-00005>
			<id-00006>
				<actions>
				</actions>
				<cast type="number">0</cast>
				<description type="formattedtext">
					<p>Starting at 2nd level, you can push yourself beyond your normal limits for a moment. On your turn, you can take one additional action on top of your regular action and a possible bonus action.</p>
					<p>Once you use this feature, you must finish a short or long rest before you can use it again. Starting at 17th level, you can use it twice before a rest, but only once on the same turn.</p>
				</description>
				<group type="string">Class</group>
				<locked type="number">1</locked>
				<name type="string">Action Surge</name>
				<prepared type="number">0</prepared>
				<source type="string">Fighter</source>
				<specializationchoice type="number">0</specializationchoice>
			</id-00006>
		</powers>
		<profbonus type="number">2</profbonus>
		<proficiencylist>
			<id-00001>
				<name type="string">Weapon: Simple weapons, martial weapons</name>
			</id-00001>
			<id-00002>
				<name type="string">Armor: All armor, shields</name>
			</id-00002>
		</proficiencylist>
		<race type="string">Dragonborn</race>
		<racelink type="windowreference">
			<class>reference_race</class>
			<recordname>race.id-00003@Incarnate-5eExpansion</recordname>
		</racelink>
		<size type="string">Medium</size>
		<skilllist>
			<id-00001>
				<name type="string">Perception</name>
				<stat type="string">wisdom</stat>
				<total type="number">0</total>
			</id-00001>
			<id-00002>
				<name type="string">Arcana</name>
				<stat type="string">intelligence</stat>
				<total type="number">1</total>
			</id-00002>
			<id-00003>
				<name type="string">Persuasion</name>
				<stat type="string">charisma</stat>
				<total type="number">0</total>
			</id-00003>
			<id-00004>
				<name type="string">Nature</name>
				<stat type="string">intelligence</stat>
				<total type="number">1</total>
			</id-00004>
			<id-00005>
				<name type="string">Medicine</name>
				<stat type="string">wisdom</stat>
				<total type="number">0</total>
			</id-00005>
			<id-00006>
				<name type="string">Survival</name>
				<stat type="string">wisdom</stat>
				<total type="number">0</total>
			</id-00006>
			<id-00007>
				<name type="string">Performance</name>
				<prof type="number">1</prof>
				<stat type="string">charisma</stat>
				<total type="number">2</total>
			</id-00007>
			<id-00008>
				<name type="string">Acrobatics</name>
				<stat type="string">dexterity</stat>
			</id-00008>
			<id-00009>
				<name type="string">Religion</name>
				<stat type="string">intelligence</stat>
				<total type="number">1</total>
			</id-00009>
			<id-00010>
				<name type="string">Athletics</name>
				<prof type="number">1</prof>
				<stat type="string">strength</stat>
				<total type="number">5</total>
			</id-00010>
			<id-00011>
				<name type="string">Sleight of Hand</name>
				<stat type="string">dexterity</stat>
			</id-00011>
			<id-00012>
				<name type="string">Insight</name>
				<prof type="number">1</prof>
				<stat type="string">wisdom</stat>
				<total type="number">2</total>
			</id-00012>
			<id-00013>
				<name type="string">Intimidation</name>
				<stat type="string">charisma</stat>
				<total type="number">0</total>
			</id-00013>
			<id-00014>
				<name type="string">Deception</name>
				<stat type="string">charisma</stat>
				<total type="number">0</total>
			</id-00014>
			<id-00015>
				<name type="string">Investigation</name>
				<stat type="string">intelligence</stat>
				<total type="number">1</total>
			</id-00015>
			<id-00016>
				<name type="string">Stealth</name>
				<stat type="string">dexterity</stat>
			</id-00016>
			<id-00017>
				<name type="string">History</name>
				<prof type="number">1</prof>
				<stat type="string">intelligence</stat>
				<total type="number">3</total>
			</id-00017>
			<id-00018>
				<name type="string">Animal Handling</name>
				<stat type="string">wisdom</stat>
				<total type="number">0</total>
			</id-00018>
		</skilllist>
		<speed>
			<armor type="number">0</armor>
			<base type="number">30</base>
			<misc type="number">0</misc>
			<temporary type="number">0</temporary>
			<total type="number">30</total>
		</speed>
		<temp>
		</temp>
		<token type="token">portrait_id-00004_token</token>
		<traitlist>
			<id-00001>
				<locked type="number">1</locked>
				<name type="string">Damage Resistance</name>
				<source type="string">Dragonborn</source>
				<text type="formattedtext">
					<h>Action Coding</h>
					<linklist>
						<link class="power" recordname="spell.typeresistanceacid@Incarnate-5eExpansion">Type Resistance (Acid)</link>
						<link class="power" recordname="spell.typeresistancecold@Incarnate-5eExpansion">Type Resistance (Cold)</link>
						<link class="power" recordname="spell.typeresistancefire@Incarnate-5eExpansion">Type Resistance (Fire)</link>
						<link class="power" recordname="spell.typeresistancelightning@Incarnate-5eExpansion">Type Resistance (Lightning)</link>
						<link class="power" recordname="spell.typeresistancepoison@Incarnate-5eExpansion">Type Resistance (Poison)</link>
					</linklist>
					<h>Description</h>
					<p>You have resistance to the damage type associated with your draconic ancestry.</p>
				</text>
				<type type="string">racial</type>
			</id-00001>
			<id-00002>
				<locked type="number">1</locked>
				<name type="string">Draconic Ancestry</name>
				<source type="string">Dragonborn</source>
				<text type="formattedtext">
					<p>You have draconic ancestry. Choose one type of dragon from the Draconic Ancestry table. Your breath weapon and damage resistance are determined by the dragon type, as shown in the table.</p>
					<p><b>Draconic Ancestry</b></p>
					<table>
						<tr>
							<td><b>Dragon</b></td>
							<td><b>Damage Type</b></td>
							<td><b>Breath Weapon</b></td>
						</tr>
						<tr>
							<td>Black</td>
							<td>Acid</td>
							<td>5 by 30 ft. line (Dex. save)</td>
						</tr>
						<tr>
							<td>Blue</td>
							<td>Lightning</td>
							<td>5 by 30 ft. line (Dex. save)</td>
						</tr>
						<tr>
							<td>Brass</td>
							<td>Fire</td>
							<td>5 by 30 ft. line (Dex. save)</td>
						</tr>
						<tr>
							<td>Bronze</td>
							<td>Lightning</td>
							<td>5 by 30 ft. line (Dex. save)</td>
						</tr>
						<tr>
							<td>Copper</td>
							<td>Acid</td>
							<td>5 by 30 ft. line (Dex. save)</td>
						</tr>
						<tr>
							<td>Gold</td>
							<td>Fire</td>
							<td>15 ft. cone (Dex. save)</td>
						</tr>
						<tr>
							<td>Green</td>
							<td>Poison</td>
							<td>15 ft. cone (Con. save)</td>
						</tr>
						<tr>
							<td>Red</td>
							<td>Fire</td>
							<td>15 ft. cone (Dex. save)</td>
						</tr>
						<tr>
							<td>Silver</td>
							<td>Cold</td>
							<td>15 ft. cone (Con. save)</td>
						</tr>
						<tr>
							<td>White</td>
							<td>Cold</td>
							<td>15 ft. cone (Con. save)</td>
						</tr>
					</table>
				</text>
				<type type="string">racial</type>
			</id-00002>
			<id-00003>
				<locked type="number">1</locked>
				<name type="string">Breath Weapon</name>
				<source type="string">Dragonborn</source>
				<text type="formattedtext">
					<h>Action Coding</h>
					<linklist>
						<link class="power" recordname="spell.breathweaponacid@Incarnate-5eExpansion">Breath Weapon (Acid)</link>
						<link class="power" recordname="spell.breathweaponcold@Incarnate-5eExpansion">Breath Weapon (Cold)</link>
						<link class="power" recordname="spell.breathweaponfire@Incarnate-5eExpansion">Breath Weapon (Fire)</link>
						<link class="power" recordname="spell.breathweaponlightning@Incarnate-5eExpansion">Breath Weapon (Lightning)</link>
						<link class="power" recordname="spell.breathweaponpoison@Incarnate-5eExpansion">Breath Weapon (Poison)</link>
					</linklist>
					<h>Description</h>
					<p>You can use your action to exhale destructive energy. Your draconic ancestry determines the size, shape, and damage type of the exhalation.</p>
					<p>When you use your breath weapon, each creature in the area of the exhalation must make a saving throw, the type of which is determined by your draconic ancestry. The DC for this saving throw equals 8 + your Constitution modifier + your proficiency bonus. A creature takes 2d6 damage on a failed save, and half as much damage on a successful one. The damage increases to 3d6 at 6th level, 4d6 at 11th level, and 5d6 at 16th level.</p>
					<p>After you use your breath weapon, you can't use it again until you complete a short or long rest.</p>
				</text>
				<type type="string">racial</type>
			</id-00003>
		</traitlist>
		<weaponlist>
			<id-00002>
				<carried type="number">2</carried>
				<damagelist>
					<id-00001>
						<dice type="dice">d6</dice>
						<stat type="string">base</stat>
						<statmult type="number">1</statmult>
						<type type="string">slashing</type>
					</id-00001>
				</damagelist>
				<isidentified type="number">1</isidentified>
				<maxammo type="number">0</maxammo>
				<name type="string">Handaxe</name>
				<prof type="number">1</prof>
				<properties type="string">Light, thrown (range 20/60)</properties>
				<shortcut type="windowreference">
					<class>item</class>
					<recordname>....inventorylist.id-00010</recordname>
				</shortcut>
				<type type="number">0</type>
			</id-00002>
			<id-00003>
				<carried type="number">2</carried>
				<damagelist>
					<id-00001>
						<dice type="dice">d6</dice>
						<stat type="string">base</stat>
						<type type="string">slashing</type>
					</id-00001>
				</damagelist>
				<isidentified type="number">1</isidentified>
				<maxammo type="number">2</maxammo>
				<name type="string">Handaxe</name>
				<prof type="number">1</prof>
				<properties type="string">Light, thrown (range 20/60)</properties>
				<shortcut type="windowreference">
					<class>item</class>
					<recordname>....inventorylist.id-00010</recordname>
				</shortcut>
				<type type="number">2</type>
			</id-00003>
			<id-00004>
				<carried type="number">2</carried>
				<damagelist>
					<id-00001>
						<dice type="dice">d4</dice>
						<stat type="string">base</stat>
						<type type="string">piercing</type>
					</id-00001>
					<id-00002>
						<dice type="dice">d4</dice>
						<type type="string">lightning</type>
					</id-00002>
				</damagelist>
				<isidentified type="number">1</isidentified>
				<maxammo type="number">0</maxammo>
				<name type="string">Dragonslayer's Spear</name>
				<prof type="number">1</prof>
				<properties type="string">Thrown (range 20/60), versatile (1d8)</properties>
				<shortcut type="windowreference">
					<class>item</class>
					<recordname>....inventorylist.id-00019</recordname>
				</shortcut>
				<type type="number">0</type>
			</id-00004>
			<id-00005>
				<carried type="number">2</carried>
				<damagelist>
					<id-00001>
						<dice type="dice">d4</dice>
						<stat type="string">base</stat>
						<type type="string">piercing</type>
					</id-00001>
					<id-00002>
						<dice type="dice">d4</dice>
						<type type="string">lightning</type>
					</id-00002>
				</damagelist>
				<isidentified type="number">1</isidentified>
				<maxammo type="number">1</maxammo>
				<name type="string">Dragonslayer's Spear</name>
				<prof type="number">1</prof>
				<properties type="string">Thrown (range 20/60), versatile (1d8)</properties>
				<shortcut type="windowreference">
					<class>item</class>
					<recordname>....inventorylist.id-00019</recordname>
				</shortcut>
				<type type="number">2</type>
			</id-00005>
		</weaponlist>
		<weight type="string">175 lbs</weight>
	</character>
</root>
