<?xml version="1.0" encoding="iso-8859-1"?>
<root version="3.3" release="8|CoreRPG:3">
	<character>
		<abilities>
			<charisma>
				<bonus type="number">-1</bonus>
				<save type="number">-1</save>
				<savemodifier type="number">0</savemodifier>
				<saveprof type="number">0</saveprof>
				<score type="number">8</score>
			</charisma>
			<constitution>
				<bonus type="number">2</bonus>
				<save type="number">5</save>
				<savemodifier type="number">0</savemodifier>
				<saveprof type="number">1</saveprof>
				<score type="number">15</score>
			</constitution>
			<dexterity>
				<bonus type="number">2</bonus>
				<save type="number">2</save>
				<savemodifier type="number">0</savemodifier>
				<saveprof type="number">0</saveprof>
				<score type="number">14</score>
			</dexterity>
			<intelligence>
				<bonus type="number">0</bonus>
				<save type="number">0</save>
				<savemodifier type="number">0</savemodifier>
				<saveprof type="number">0</saveprof>
				<score type="number">10</score>
			</intelligence>
			<strength>
				<bonus type="number">3</bonus>
				<save type="number">6</save>
				<savemodifier type="number">0</savemodifier>
				<saveprof type="number">1</saveprof>
				<score type="number">16</score>
			</strength>
			<wisdom>
				<bonus type="number">-1</bonus>
				<save type="number">-1</save>
				<savemodifier type="number">0</savemodifier>
				<saveprof type="number">0</saveprof>
				<score type="number">9</score>
			</wisdom>
		</abilities>
		<adventurelist>
		</adventurelist>
		<age type="string">40</age>
		<alignment type="string">Chaotic Neutral</alignment>
		<background type="string">Soldier</background>
		<backgroundlink type="windowreference">
			<class>reference_background</class>
			<recordname>reference.backgrounddata.soldier@DD PHB Deluxe</recordname>
		</backgroundlink>
		<bonds type="string">My honor is my life.</bonds>
		<classes>
			<id-00001>
				<casterlevelinvmult type="number">0</casterlevelinvmult>
				<casterpactmagic type="number">0</casterpactmagic>
				<hddie type="dice">d12</hddie>
				<hdused type="number">0</hdused>
				<level type="number">6</level>
				<name type="string">Barbarian</name>
				<shortcut type="windowreference">
					<class>reference_class</class>
					<recordname>reference.classdata.barbarian@DD PHB Deluxe</recordname>
				</shortcut>
			</id-00001>
		</classes>
		<coins>
			<slot1>
				<amount type="number">215</amount>
				<name type="string">GP</name>
			</slot1>
			<slot2>
				<amount type="number">0</amount>
				<name type="string">PP</name>
			</slot2>
			<slot3>
				<amount type="number">155</amount>
				<name type="string">SP</name>
			</slot3>
			<slot4>
				<amount type="number">0</amount>
			</slot4>
			<slot5>
				<amount type="number">146</amount>
				<name type="string">CP</name>
			</slot5>
			<slot6>
				<amount type="number">0</amount>
			</slot6>
		</coins>
		<defenses>
			<ac>
				<armor type="number">0</armor>
				<disstealth type="number">0</disstealth>
				<misc type="number">0</misc>
				<prof type="number">1</prof>
				<shield type="number">0</shield>
				<stat2 type="string">constitution</stat2>
				<temporary type="number">0</temporary>
				<total type="number">14</total>
			</ac>
			<special type="string">Of Hades</special>
		</defenses>
		<encumbrance>
			<encumbered type="number">80</encumbered>
			<encumberedheavy type="number">160</encumberedheavy>
			<liftpushdrag type="number">480</liftpushdrag>
			<load type="number">95.2</load>
			<max type="number">240</max>
		</encumbrance>
		<exp type="number">634</exp>
		<expneeded type="number">700</expneeded>
		<featlist>
			<id-00001>
				<locked type="number">1</locked>
				<name type="string">Tavern Brawler</name>
				<text type="formattedtext">
					<p>Accustomed to rough-and-tumble fighting using whatever weapons happen to be at hand, you gain the following benefits:</p>
					<list>
						<li>Increase your Strength or Constitution score by 1, to a maximum of 20.</li>
						<li>You are proficient with improvised weapons.</li>
						<li>Your unarmed strike uses a d4 for damage.</li>
						<li>When you hit a creature with an unarmed strike or an improvised weapon on your turn, you can use a bonus action to attempt to grapple the target.</li>
					</list>
				</text>
			</id-00001>
			<id-00002>
				<name type="string">Mild Telekenetic</name>
				<text type="formattedtext">
					<p>You can apply the force of 1 pound to an object up to 15 feet away from you. This ability lasts for 10 minutes. You must finish a short or long rest before you can use this feature again.</p>
				</text>
			</id-00002>
		</featlist>
		<featurelist>
			<id-00001>
				<locked type="number">1</locked>
				<name type="string">Military Rank</name>
				<source type="string">Soldier</source>
				<text type="formattedtext">
					<p>You have a military rank from your career as a soldier.</p>
					<p>Soldiers loyal to your former military organization still recognize your authority and influence, and they defer to you if they are of a lower rank. You can invoke your rank to exert influence over other soldiers and requisition simple equipment or horses for temporary use. You can also usually gain access to friendly military encampments and fortresses where your rank is recognized.</p>
				</text>
			</id-00001>
			<id-00002>
				<level type="number">1</level>
				<locked type="number">1</locked>
				<name type="string">Rage</name>
				<source type="string">Barbarian</source>
				<text type="formattedtext">
					<p>In battle, you fight with primal ferocity. On your turn, you can enter a rage as a bonus action. While raging, you gain the following benefits if you aren't wearing heavy armor:</p>
					<list>
						<li>You have advantage on Strength checks and Strength saving throws.</li>
						<li>When you make a melee weapon attack using Strength, you gain a bonus to the damage roll that increases as you gain levels as a barbarian, as shown in the Rage Damage column of the Barbarian table.</li>
						<li>You have resistance to bludgeoning, piercing, and slashing damage.</li>
					</list>
					<p>If you are able to cast spells, you can't cast them while raging.</p>
					<p>Your rage lasts for 1 minute. It ends early if you are knocked unconscious or if your turn ends and you have neither attacked a hostile creature since your last turn nor taken damage since then. You can also end your rage as a bonus action on your turn</p>
					<p>Once you have raged the number of times shown for your barbarian level in the Rages column of the Barbarian table, you must finish a long rest before you can rage again.</p>
				</text>
			</id-00002>
			<id-00003>
				<level type="number">1</level>
				<locked type="number">1</locked>
				<name type="string">Unarmored Defense</name>
				<source type="string">Barbarian</source>
				<text type="formattedtext">
					<p>While you are not wearing any armor, your Armor Class equals 10 + your Dexterity modifier + your Constitution modifier. You can use a shield and still gain this benefit.</p>
				</text>
			</id-00003>
			<id-00004>
				<level type="number">2</level>
				<locked type="number">1</locked>
				<name type="string">Reckless Attack</name>
				<source type="string">Barbarian</source>
				<text type="formattedtext">
					<p>Starting at 2nd level, you can throw aside all concern for defense and attack with fierce desperation. When you make your first attack on your turn, you can decide to attack recklessly. Doing so gives you advantage on melee weapon attack rolls using Strength during this turn, but attack rolls against you have advantage until your next turn.</p>
				</text>
			</id-00004>
			<id-00005>
				<level type="number">2</level>
				<locked type="number">1</locked>
				<name type="string">Danger Sense</name>
				<source type="string">Barbarian</source>
				<text type="formattedtext">
					<p>At 2nd level, you gain an uncanny sense of when things nearby aren't as they should be, giving you an edge when you dodge away from danger.</p>
					<p>You have advantage on Dexterity saving throws against effects that originate within 30 feet of you, such as a trap or a spellcaster within that range. To gain this benefit, you cannot be blinded, deafened, or incapacitated.</p>
				</text>
			</id-00005>
			<id-00006>
				<level type="number">1</level>
				<locked type="number">1</locked>
				<name type="string">Path of the Berserker</name>
				<source type="string">Barbarian</source>
				<text type="formattedtext">
					<p>For some barbarians, rage is a means to an end-that end being violence. The Path of the Berserker is a path of untrammeled fury, slick with blood. As you enter the berserker's rage, you thrill in the chaos of battle, heedless of your own health or well-being.</p>
					<h>Features</h>
					<linklist>
						<link class="reference_classfeature" recordname="reference.classdata.barbarian.features.frenzy3@DD PHB Deluxe">Frenzy</link>
						<link class="reference_classfeature" recordname="reference.classdata.barbarian.features.mindlessrage6@DD PHB Deluxe">Mindless Rage</link>
						<link class="reference_classfeature" recordname="reference.classdata.barbarian.features.intimidatingpresence10@DD PHB Deluxe">Intimidating Presence</link>
						<link class="reference_classfeature" recordname="reference.classdata.barbarian.features.retaliation14@DD PHB Deluxe">Retaliation</link>
					</linklist>
				</text>
			</id-00006>
			<id-00007>
				<level type="number">3</level>
				<locked type="number">1</locked>
				<name type="string">Frenzy</name>
				<source type="string">Barbarian</source>
				<specialization type="string">Path of the Berserker</specialization>
				<text type="formattedtext">
					<p>Starting when you choose this path at 3rd level, when you rage you can choose to go into a frenzy. If you do so, for the duration of your rage you can make a single melee weapon attack as a bonus action each turn. When your rage ends, you suffer one level of exhaustion (as described in the conditions appendix).</p>
				</text>
			</id-00007>
			<id-00008>
				<level type="number">4</level>
				<locked type="number">1</locked>
				<name type="string">Ability Score Improvement - Tavern Brawler</name>
				<source type="string">Barbarian</source>
				<specializationchoice type="number">0</specializationchoice>
				<text type="formattedtext">
					<p>When you reach 4th level, and again at 8th, 12th, 16th, and 19th level, you can increase one ability score of your choice by 2, or you can increase two ability scores of your choice by 1. As normal, you can't increase an ability score above 20 using this feature.</p>
				</text>
			</id-00008>
			<id-00009>
				<level type="number">5</level>
				<locked type="number">1</locked>
				<name type="string">Fast Movement</name>
				<source type="string">Barbarian</source>
				<specializationchoice type="number">0</specializationchoice>
				<text type="formattedtext">
					<p>Starting at 5th level, you speed increases by 10 feet while you aren't wearing heavy armor.</p>
				</text>
			</id-00009>
			<id-00010>
				<level type="number">5</level>
				<locked type="number">1</locked>
				<name type="string">Extra Attack</name>
				<source type="string">Barbarian</source>
				<specializationchoice type="number">0</specializationchoice>
				<text type="formattedtext">
					<p>Beginning at 5th level, you can attack twice, instead of once, whenever you take the Attack action on your turn.</p>
				</text>
			</id-00010>
			<id-00011>
				<level type="number">6</level>
				<locked type="number">1</locked>
				<name type="string">Mindless Rage</name>
				<source type="string">Barbarian</source>
				<specialization type="string">Path of the Berserker</specialization>
				<specializationchoice type="number">0</specializationchoice>
				<text type="formattedtext">
					<h>Effect Coding</h>
					<linklist>
						<link class="power" recordname="spell.mindlessrage@Incarnate-5eExpansion">Mindless Rage</link>
						<link class="charsheet" recordname="charsheet.id-00002@Incarnate-5eExpansion"></link>
					</linklist>
					<h>Description</h>
					<p>Beginning at 6th level, you can't be charmed or frightened while raging. If you are charmed or frightened when you enter your rage, the effect is suspended for the duration of the rage.</p>
				</text>
			</id-00011>
		</featurelist>
		<flaws type="string">My hunger for my enemies is blind and unreasoning.</flaws>
		<gender type="string">Male</gender>
		<height type="string">3'7&#34;</height>
		<hp>
			<deathsavefail type="number">0</deathsavefail>
			<deathsavesuccess type="number">0</deathsavesuccess>
			<temporary type="number">0</temporary>
			<total type="number">59</total>
			<wounds type="number">0</wounds>
		</hp>
		<ideals type="string">Independence. When people follow orders blindly, they embrace a kind of tyranny. (Chaotic)</ideals>
		<initiative>
			<misc type="number">0</misc>
			<temporary type="number">0</temporary>
			<total type="number">2</total>
		</initiative>
		<inspiration type="number">0</inspiration>
		<inventorylist>
			<id-00001>
				<carried type="number">1</carried>
				<cost type="string">1 gp</cost>
				<count type="number">1</count>
				<isidentified type="number">1</isidentified>
				<location type="string">Backpack</location>
				<locked type="number">1</locked>
				<name type="string">Bedroll</name>
				<subtype type="string">Standard</subtype>
				<type type="string">Adventuring Gear</type>
				<weight type="number">7</weight>
			</id-00001>
			<id-00002>
				<carried type="number">1</carried>
				<cost type="string">5 sp</cost>
				<count type="number">10</count>
				<description type="formattedtext">
					<p>Rations consist of dry foods suitable for extended travel, including jerky, dried fruit, hardtack, and nuts.</p>
				</description>
				<isidentified type="number">1</isidentified>
				<location type="string">Backpack</location>
				<locked type="number">1</locked>
				<name type="string">Rations (1 Day)</name>
				<subtype type="string">Standard</subtype>
				<type type="string">Adventuring Gear</type>
				<weight type="number">2</weight>
			</id-00002>
			<id-00003>
				<carried type="number">1</carried>
				<cost type="string">1 cp</cost>
				<count type="number">10</count>
				<description type="formattedtext">
					<p>A torch burns for 1 hour, providing bright light in a 20-foot radius and dim light for an additional 20 feet. If you make a melee attack with a burning torch and hit, it deals 1 fire damage.</p>
				</description>
				<isidentified type="number">1</isidentified>
				<location type="string">Backpack</location>
				<locked type="number">1</locked>
				<name type="string">Torch</name>
				<subtype type="string">Standard</subtype>
				<type type="string">Adventuring Gear</type>
				<weight type="number">1</weight>
			</id-00003>
			<id-00004>
				<carried type="number">1</carried>
				<cost type="string">5 sp</cost>
				<count type="number">1</count>
				<description type="formattedtext">
					<p>This small container holds flint, fire steel, and tinder (usually dry cloth soaked in light oil) used to kindle a fire. Using it to light a torch-or anything else with abundant, exposed fuel-takes an action. Lighting any other fire takes 1 minute.</p>
				</description>
				<isidentified type="number">1</isidentified>
				<location type="string">Backpack</location>
				<locked type="number">1</locked>
				<name type="string">Tinderbox</name>
				<subtype type="string">Standard</subtype>
				<type type="string">Adventuring Gear</type>
				<weight type="number">1</weight>
			</id-00004>
			<id-00005>
				<carried type="number">1</carried>
				<cost type="string">2 sp</cost>
				<count type="number">1</count>
				<isidentified type="number">1</isidentified>
				<location type="string">Backpack</location>
				<locked type="number">1</locked>
				<name type="string">Waterskin</name>
				<subtype type="string">Standard</subtype>
				<type type="string">Adventuring Gear</type>
				<weight type="number">5</weight>
			</id-00005>
			<id-00006>
				<carried type="number">1</carried>
				<cost type="string">2 sp</cost>
				<count type="number">1</count>
				<description type="formattedtext">
					<p>This tin box contains a cup and simple cutlery. The box clamps together, and one side can be used as a cooking pan and the other as a plate or shallow bowl.</p>
				</description>
				<isidentified type="number">1</isidentified>
				<location type="string">Backpack</location>
				<locked type="number">1</locked>
				<name type="string">Mess Kit</name>
				<subtype type="string">Equipment Kits</subtype>
				<type type="string">Adventuring Gear</type>
				<weight type="number">1</weight>
			</id-00006>
			<id-00007>
				<carried type="number">1</carried>
				<cost type="string">1 gp</cost>
				<count type="number">1</count>
				<isidentified type="number">1</isidentified>
				<location type="string">Backpack</location>
				<locked type="number">1</locked>
				<name type="string">Rope, Hempen (50 Feet)</name>
				<subtype type="string">Standard</subtype>
				<type type="string">Adventuring Gear</type>
				<weight type="number">10</weight>
			</id-00007>
			<id-00008>
				<carried type="number">1</carried>
				<cost type="string">2 gp</cost>
				<count type="number">1</count>
				<isidentified type="number">1</isidentified>
				<locked type="number">1</locked>
				<name type="string">Backpack</name>
				<subtype type="string">Standard</subtype>
				<type type="string">Adventuring Gear</type>
				<weight type="number">5</weight>
			</id-00008>
			<id-00009>
				<carried type="number">2</carried>
				<cost type="string">10 gp</cost>
				<count type="number">1</count>
				<damage type="string">1d8 slashing</damage>
				<isidentified type="number">1</isidentified>
				<locked type="number">1</locked>
				<name type="string">Battleaxe</name>
				<properties type="string">Versatile (1d10)</properties>
				<subtype type="string">Martial Weapons</subtype>
				<type type="string">Weapon</type>
				<weight type="number">4</weight>
			</id-00009>
			<id-00010>
				<ac type="number">0</ac>
				<bonus type="number">0</bonus>
				<carried type="number">2</carried>
				<cost type="string">5 sp</cost>
				<count type="number">3</count>
				<damage type="string">1d6 piercing</damage>
				<description type="formattedtext">
					<p></p>
				</description>
				<isidentified type="number">1</isidentified>
				<location type="string">Backpack</location>
				<locked type="number">1</locked>
				<name type="string">Javelin</name>
				<properties type="string">Thrown (range 30/120)</properties>
				<subtype type="string">Simple Melee Weapons</subtype>
				<type type="string">Weapon</type>
				<weight type="number">2</weight>
			</id-00010>
			<id-00011>
				<carried type="number">2</carried>
				<cost type="string">5 gp</cost>
				<count type="number">2</count>
				<damage type="string">1d6 slashing</damage>
				<isidentified type="number">1</isidentified>
				<location type="string">Belt</location>
				<locked type="number">1</locked>
				<name type="string">Handaxe</name>
				<properties type="string">Light, thrown (range 20/60)</properties>
				<subtype type="string">Simple Melee Weapons</subtype>
				<type type="string">Weapon</type>
				<weight type="number">2</weight>
			</id-00011>
			<id-00012>
				<carried type="number">1</carried>
				<cost type="string">1 sp</cost>
				<count type="number">1</count>
				<description type="formattedtext">
					<p>This item encompasses a wide range of game pieces, including dice and decks of cards (for games such as Three-Dragon Ante). A few common examples appear on the Tools table, but other kinds of gaming sets exist. If you are proficient with a gaming set, you can add your proficiency bonus to ability checks you make to play a game with that set. Each type of gaming set requires a separate proficiency.</p>
				</description>
				<isidentified type="number">1</isidentified>
				<location type="string">Backpack</location>
				<locked type="number">1</locked>
				<name type="string">Knuckle-bone Dice Set</name>
				<subtype type="string">Gaming Set</subtype>
				<type type="string">Tools</type>
				<weight type="number">0</weight>
			</id-00012>
			<id-00013>
				<carried type="number">2</carried>
				<cost type="string">5 gp</cost>
				<count type="number">1</count>
				<description type="formattedtext">
					<p>A holy symbol is a representation of a god or pantheon. It might be an amulet depicting a symbol representing a deity, the same symbol carefully engraved or inlaid as an emblem on a shield, or a tiny box holding a fragment of a sacred relic. The Player's Handbook lists many gods in the multiverse and their typical symbols. A cleric or paladin can use a holy symbol as a spellcasting focus, as described in chapter To use the symbol in this way, the caster must hold it in hand, wear it visibly, or bear it on a shield.</p>
				</description>
				<isidentified type="number">1</isidentified>
				<location type="string">Belt</location>
				<locked type="number">1</locked>
				<name type="string">Insignia Amulet</name>
				<subtype type="string">Holy Symbol</subtype>
				<type type="string">Adventuring Gear</type>
				<weight type="number">1</weight>
			</id-00013>
			<id-00014>
				<carried type="number">2</carried>
				<cost type="string">5 sp</cost>
				<count type="number">1</count>
				<isidentified type="number">1</isidentified>
				<locked type="number">1</locked>
				<name type="string">Clothes, Common</name>
				<subtype type="string">Standard</subtype>
				<type type="string">Adventuring Gear</type>
				<weight type="number">3</weight>
			</id-00014>
			<id-00015>
				<carried type="number">1</carried>
				<count type="number">1</count>
				<isidentified type="number">1</isidentified>
				<location type="string">Belt</location>
				<name type="string">Flat bone with dry, hairy skin</name>
				<weight type="number">0.2</weight>
			</id-00015>
			<id-00016>
				<ac type="number">0</ac>
				<bonus type="number">0</bonus>
				<carried type="number">1</carried>
				<cost type="string">priceless</cost>
				<count type="number">1</count>
				<description type="formattedtext">
					<h>Effect Coding</h>
					<linklist>
						<link class="power" recordname="spell.heartstone@Incarnate-5eExpansion">Heartstone</link>
					</linklist>
					<h>Description</h>
					<p>By concentrating on this stone for 1 minute you are teleported into the Nexus, a place of safety for most adventurers. (It is your ticket back, so guard it with your life.)</p>
				</description>
				<isidentified type="number">1</isidentified>
				<location type="string">Belt</location>
				<locked type="number">1</locked>
				<name type="string">Heartstone</name>
				<nonid_name type="string">Heartstone</nonid_name>
				<rarity type="string">legendary</rarity>
				<subtype type="string">Standard</subtype>
				<type type="string">Adventuring Gear</type>
				<weight type="number">1</weight>
			</id-00016>
			<id-00017>
				<ac type="number">0</ac>
				<bonus type="number">0</bonus>
				<carried type="number">2</carried>
				<cost type="string">900 GP</cost>
				<count type="number">1</count>
				<description type="formattedtext">
					<p>This helm has 3 charges. While wearing it, you can use an action and expend 1 charge to cast the teleport spell from it. The helm regains 1d3 expended charges daily at dawn.</p>
					<linklist>
						<link class="power" recordname="spell.teleport@Incarnate-5eExpansion">Teleport</link>
					</linklist>
				</description>
				<isidentified type="number">1</isidentified>
				<locked type="number">0</locked>
				<name type="string">Helm of Teleportation</name>
				<nonid_name type="string">Bronze Helm</nonid_name>
				<nonidentified type="string">Taken from a young red dragon.</nonidentified>
				<rarity type="string">rare (requires attunement)</rarity>
				<type type="string">Wondrous Item</type>
				<weight type="number">3</weight>
			</id-00017>
			<id-00018>
				<ac type="number">0</ac>
				<bonus type="number">0</bonus>
				<carried type="number">1</carried>
				<cost type="string">1GP</cost>
				<count type="number">11</count>
				<description type="formattedtext">
					<p>same as 1 ration.</p>
					<p>Constitution saving throw of 14 or date 1d4 poison damage</p>
				</description>
				<isidentified type="number">0</isidentified>
				<locked type="number">1</locked>
				<name type="string">rotten snake meat</name>
				<nonid_name type="string">Rotten snake meat</nonid_name>
				<weight type="number">1</weight>
			</id-00018>
			<id-00019>
				<ac type="number">0</ac>
				<bonus type="number">0</bonus>
				<carried type="number">1</carried>
				<cost type="string">1,000 GV</cost>
				<count type="number">1</count>
				<damage type="string">1d8 necrotic, magic</damage>
				<description type="formattedtext">
					<p>This Boomerang of Hades may be attuned to two creatures at a time, one primary, one secondary. To bind as a primary you must make a competing wisdom save against the current primary owner. If you attune and do not win the competition then you bind to the secondary slot. You cannot choose to unatune it, but someone else may attune to it taking over the secondary slot. You may only attempt to take primary ownership during an equinox.</p>
					<p><b>Binding of Engagement: </b>This boomerang is attached to your life essence. When not in use, it magically shrinks to perfectly fit one of your fingers. No one but the primary binding can remove it from you. If you loose the finger/hand/arm then the ring detaches itself and flies to seek out your life essence and reattach itself to you. As a bonus action you may remove it as a throwable weapon (a boomerang). It magically retuns to your finger at sunset.</p>
					<p><b>Farwatching </b>: the primary individual can see true vision through the boomerang for 30 ft.</p>
					<p><b>Farspeaking </b>: the primary individual can speak telepathically to the secondary binding.</p>
					<p>Only a servant of Hades can touch the handle of this weapon (to all others it is a beam of pure darkness)</p>
					<p>Level: 1</p>
					<p><b>Prestige 0:</b></p>
					<p>+0 magic weapon, necrotic damage</p>
					<p>If you throw the spear and it misses it flies back to your hand.</p>
					<p>Range (30/90)</p>
					<p><b>Prestige 1:</b></p>
					<p>+1 magic weapon, necrotic damage</p>
					<p>If you throw the boomerang and it hits or misses it flies back to your hand.</p>
					<p>Range (40/120)</p>
					<p><b>Prestige 2:</b></p>
					<p>+1 magic weapon, necrotic damage</p>
					<p>The boomerang will return itself to you if ever separated for more than a minute.</p>
					<p><b>Prestige 3:</b></p>
					<p>+2 magic weapon, necrotic damage</p>
					<p>The boomerang will return itself to you if ever separated for more than a minute.</p>
					<p>It scores a critical hit on a roll of 19 or 20.</p>
					<p>Range (60/180)</p>
					<p><b>Prestige 4:</b></p>
					<p>+3 magic weapon, necrotic damage</p>
					<p>The boomerang will try to return itself to you if ever separated.</p>
					<p>It scores a critical hit on a roll of 19 or 20.</p>
					<p>This ring allows you to see normally in dim light, darkness, and magical darkness.</p>
					<p>Once per short rest you may cast a lvl 7 darkness from the ring.</p>
					<p>Range (70/210)</p>
				</description>
				<isidentified type="number">0</isidentified>
				<locked type="number">1</locked>
				<name type="string">Boomerang of Hades - Prestige 0</name>
				<nonid_name type="string">Boomerang of the Hidden Champion</nonid_name>
				<properties type="string">Thrown (range 30/90), versatile (1d8)</properties>
				<rarity type="string">Very Rare</rarity>
				<subtype type="string">Simple Melee Weapons</subtype>
				<type type="string">Weapon</type>
				<weight type="number">3</weight>
			</id-00019>
		</inventorylist>
		<languagelist>
			<id-00001>
				<name type="string">Common</name>
			</id-00001>
			<id-00002>
				<name type="string">Gnomish</name>
			</id-00002>
		</languagelist>
		<level type="number">6</level>
		<name type="string">Jarise Highplate</name>
		<notes type="string">Log of Meals --\nRotten Snake meat - *\nDeath Elemental - 1d6 necrotic\nGoblin - *, Well Marinated\nDemon - Wisdom dropped by three and gained mild telekenetic feat, Char-Grilled\nMagma Mephit - 2d8 fire, Spicy\nGiant Wolf Spider - 2d6 poison, Crunchy, Tangy\nOgre - Chewy, Gritty\nPanther - Tender</notes>
		<perception type="number">12</perception>
		<perceptionmodifier type="number">0</perceptionmodifier>
		<personalitytraits type="string">I enjoy being strong and like breaking things.\nI have a crude sense of humor.</personalitytraits>
		<powerdisplaymode type="string">action</powerdisplaymode>
		<powergroup>
			<id-00001>
				<castertype type="string">memorization</castertype>
				<name type="string">Spells</name>
			</id-00001>
			<id-00002>
				<name type="string">ATT</name>
			</id-00002>
			<id-00004>
				<atkprof type="number">1</atkprof>
				<name type="string">Class</name>
				<saveprof type="number">1</saveprof>
			</id-00004>
		</powergroup>
		<powermeta>
			<pactmagicslots1>
				<max type="number">0</max>
				<used type="number">0</used>
			</pactmagicslots1>
			<pactmagicslots2>
				<max type="number">0</max>
				<used type="number">0</used>
			</pactmagicslots2>
			<pactmagicslots3>
				<max type="number">0</max>
				<used type="number">0</used>
			</pactmagicslots3>
			<pactmagicslots4>
				<max type="number">0</max>
				<used type="number">0</used>
			</pactmagicslots4>
			<pactmagicslots5>
				<max type="number">0</max>
				<used type="number">0</used>
			</pactmagicslots5>
			<pactmagicslots6>
				<max type="number">0</max>
				<used type="number">0</used>
			</pactmagicslots6>
			<pactmagicslots7>
				<max type="number">0</max>
				<used type="number">0</used>
			</pactmagicslots7>
			<pactmagicslots8>
				<max type="number">0</max>
				<used type="number">0</used>
			</pactmagicslots8>
			<pactmagicslots9>
				<max type="number">0</max>
				<used type="number">0</used>
			</pactmagicslots9>
			<spellslots1>
				<max type="number">0</max>
				<used type="number">0</used>
			</spellslots1>
			<spellslots2>
				<max type="number">0</max>
				<used type="number">0</used>
			</spellslots2>
			<spellslots3>
				<max type="number">0</max>
				<used type="number">0</used>
			</spellslots3>
			<spellslots4>
				<max type="number">0</max>
				<used type="number">0</used>
			</spellslots4>
			<spellslots5>
				<max type="number">0</max>
				<used type="number">0</used>
			</spellslots5>
			<spellslots6>
				<max type="number">0</max>
				<used type="number">0</used>
			</spellslots6>
			<spellslots7>
				<max type="number">0</max>
				<used type="number">0</used>
			</spellslots7>
			<spellslots8>
				<max type="number">0</max>
				<used type="number">0</used>
			</spellslots8>
			<spellslots9>
				<max type="number">0</max>
				<used type="number">0</used>
			</spellslots9>
		</powermeta>
		<powermode type="string">combat</powermode>
		<powers>
			<id-00001>
				<actions>
					<id-00002>
						<heallist>
							<id-00001>
								<bonus type="number">2</bonus>
								<dice type="dice">d4,d4</dice>
							</id-00001>
						</heallist>
						<order type="number">1</order>
						<type type="string">heal</type>
					</id-00002>
				</actions>
				<cast type="number">0</cast>
				<description type="formattedtext">
					<p>A character who drinks the magical red fluid in this vial regains 2d4 + 2 hit points. Drinking or administering a potion takes an action.</p>
				</description>
				<level type="number">0</level>
				<locked type="number">1</locked>
				<name type="string">Potion of Healing</name>
				<prepared type="number">0</prepared>
				<shortdescription type="string">2d4 + 2 healing</shortdescription>
			</id-00001>
			<id-00002>
				<actions>
					<id-00001>
						<durmod type="number">1</durmod>
						<durunit type="string">minute</durunit>
						<label type="string">ADVCHK: strength; ADVSAV: strength; DMG: 2 melee; RESIST: bludgeoning, piercing, slashing; Immune to frightened and charmed</label>
						<order type="number">1</order>
						<targeting type="string">self</targeting>
						<type type="string">effect</type>
					</id-00001>
				</actions>
				<cast type="number">0</cast>
				<description type="formattedtext">
					<p>In battle, you fight with primal ferocity. On your turn, you can enter a rage as a bonus action. While raging, you gain the following benefits if you aren't wearing heavy armor:</p>
					<list>
						<li>You have advantage on Strength checks and Strength saving throws.</li>
						<li>When you make a melee weapon attack using Strength, you gain a bonus to the damage roll that increases as you gain levels as a barbarian, as shown in the Rage Damage column of the Barbarian table.</li>
						<li>You have resistance to bludgeoning, piercing, and slashing damage.</li>
					</list>
					<p>If you are able to cast spells, you can't cast them while raging.</p>
					<p>Your rage lasts for 1 minute. It ends early if you are knocked unconscious or if your turn ends and you have neither attacked a hostile creature since your last turn nor taken damage since then. You can also end your rage as a bonus action on your turn</p>
					<p>Once you have raged the number of times shown for your barbarian level in the Rages column of the Barbarian table, you must finish a long rest before you can rage again.</p>
				</description>
				<group type="string">Class</group>
				<level type="number">0</level>
				<locked type="number">1</locked>
				<name type="string">*Rage</name>
				<prepared type="number">3</prepared>
				<source type="string">Barbarian</source>
			</id-00002>
			<id-00003>
				<actions>
					<id-00001>
						<label type="string">Danger Sense 30ft; ADVSAV: dexterity</label>
						<order type="number">1</order>
						<targeting type="string">self</targeting>
						<type type="string">effect</type>
					</id-00001>
				</actions>
				<cast type="number">0</cast>
				<description type="formattedtext">
					<p>At 2nd level, you gain an uncanny sense of when things nearby aren't as they should be, giving you an edge when you dodge away from danger.</p>
					<p>You have advantage on Dexterity saving throws against effects that originate within 30 feet of you, such as a trap or a spellcaster within that range. To gain this benefit, you cannot be blinded, deafened, or incapacitated.</p>
				</description>
				<group type="string">Class</group>
				<level type="number">0</level>
				<locked type="number">1</locked>
				<name type="string">Danger Sense</name>
				<prepared type="number">0</prepared>
				<source type="string">Barbarian</source>
			</id-00003>
			<id-00004>
				<actions>
					<id-00001>
						<label type="string">ADVATK; GRANTADVATK</label>
						<order type="number">1</order>
						<targeting type="string">self</targeting>
						<type type="string">effect</type>
					</id-00001>
				</actions>
				<cast type="number">0</cast>
				<description type="formattedtext">
					<p>Starting at 2nd level, you can throw aside all concern for defense and attack with fierce desperation. When you make your first attack on your turn, you can decide to attack recklessly. Doing so gives you advantage on melee weapon attack rolls using Strength during this turn, but attack rolls against you have advantage until your next turn.</p>
				</description>
				<group type="string">Class</group>
				<level type="number">0</level>
				<locked type="number">1</locked>
				<name type="string">Reckless Attack</name>
				<prepared type="number">0</prepared>
				<ritual type="number">0</ritual>
				<source type="string">Barbarian</source>
			</id-00004>
			<id-00005>
				<actions>
					<id-00001>
						<apply type="string">roll</apply>
						<label type="string">DMG: [-STR]</label>
						<order type="number">1</order>
						<targeting type="string">self</targeting>
						<type type="string">effect</type>
					</id-00001>
				</actions>
				<cast type="number">0</cast>
				<level type="number">0</level>
				<name type="string">Offhand</name>
				<prepared type="number">0</prepared>
			</id-00005>
			<id-00006>
				<actions>
					<id-00001>
						<durmod type="number">1</durmod>
						<durunit type="string">day</durunit>
						<label type="string">Exhaustion Level 1; DISCHK</label>
						<order type="number">1</order>
						<targeting type="string">self</targeting>
						<type type="string">effect</type>
					</id-00001>
					<id-00002>
						<durmod type="number">3</durmod>
						<durunit type="string">day</durunit>
						<label type="string">Exhaustion Level 3; DISSAV; DISATK</label>
						<order type="number">2</order>
						<targeting type="string">self</targeting>
						<type type="string">effect</type>
					</id-00002>
					<id-00003>
						<label type="string">Attack as a bonus, Exhaustion on end</label>
						<order type="number">3</order>
						<targeting type="string">self</targeting>
						<type type="string">effect</type>
					</id-00003>
				</actions>
				<cast type="number">0</cast>
				<description type="formattedtext">
					<linklist>
						<link class="encounter" recordname="encounter.id-00004@Incarnate-5eExpansion">Exhaustion</link>
					</linklist>
				</description>
				<group type="string">Class</group>
				<level type="number">0</level>
				<locked type="number">1</locked>
				<name type="string">Frenzied Hunger</name>
				<prepared type="number">0</prepared>
				<ritual type="number">0</ritual>
			</id-00006>
			<id-00007>
				<actions>
				</actions>
				<cast type="number">0</cast>
				<description type="formattedtext">
					<p>You can apply the force of 1 pound to an object up to 15 feet away from you. This ability lasts for 10 minutes. You must finish a short or long rest before you can use this feature again.</p>
				</description>
				<level type="number">0</level>
				<locked type="number">1</locked>
				<name type="string">Mild Telekenetic</name>
				<prepared type="number">1</prepared>
				<usesperiod type="string">enc</usesperiod>
			</id-00007>
			<id-00008>
				<actions>
					<id-00001>
						<damagelist>
							<id-00001>
								<dice type="dice">d10,d10,d10</dice>
								<type type="string">force</type>
							</id-00001>
						</damagelist>
						<order type="number">1</order>
						<type type="string">damage</type>
					</id-00001>
				</actions>
				<cast type="number">0</cast>
				<castingtime type="string">1 action</castingtime>
				<components type="string">V</components>
				<description type="formattedtext">
					<p>This spell instantly transports you and up to eight willing creatures of your choice that you can see within range, or a single object that you can see within range, to a destination you select. If you target an object, it must be able to fit entirely inside a 10-foot cube, and it can't be held or carried by an unwilling creature. The destination you choose must be known to you, and it must be on the same plane of existence as you. Your familiarity with the destination determines whether you arrive there successfully. The GM rolls d100 and consults the table.</p>
					<table>
						<tr>
							<td colspan="2"><b>Familiarity</b></td>
							<td><b>Mishap</b></td>
							<td><b>Similar Area</b></td>
							<td><b>Off Target</b></td>
							<td><b>On Target</b></td>
						</tr>
						<tr>
							<td colspan="2">Permanent circle</td>
							<td>-</td>
							<td>-</td>
							<td>-</td>
							<td>01-100</td>
						</tr>
						<tr>
							<td colspan="2">Associated object</td>
							<td>-</td>
							<td>-</td>
							<td>-</td>
							<td>01-100</td>
						</tr>
						<tr>
							<td colspan="2">Very familiar</td>
							<td>01-05</td>
							<td>06-13</td>
							<td>14-24</td>
							<td>25-100</td>
						</tr>
						<tr>
							<td colspan="2">Seen casually</td>
							<td>01-33</td>
							<td>34-43</td>
							<td>44-53</td>
							<td>54-100</td>
						</tr>
						<tr>
							<td colspan="2">Viewed once</td>
							<td>01-43</td>
							<td>44-53</td>
							<td>54-73</td>
							<td>74-100</td>
							<td>Description</td>
							<td>01-43</td>
							<td>44-53</td>
							<td>54-73</td>
							<td>74-100</td>
						</tr>
						<tr>
							<td colspan="2">False destination</td>
							<td>01-50</td>
							<td>51-100</td>
							<td>-</td>
							<td>-</td>
						</tr>
					</table>
					<p><b>Familiarity </b>. &#34;Permanent circle&#34; means a permanent teleportation circle whose sigil sequence you know. &#34;Associated object&#34; means that you possess an object taken from the desired destination within the last six months, such as a book from a wizard's library, bed linen from a royal suite, or a chunk of marble from a lich's secret tomb. &#34;Very familiar&#34; is a place you have been very often, a place you have carefully studied, or a place you can see when you cast the spell. &#34;Seen casually&#34; is someplace you have seen more than once but with which you aren't very familiar. &#34;Viewed once&#34; is a place you have seen once, possibly using magic. &#34;Description&#34; is a place whose location and appearance you know through someone else's description, perhaps from a map. &#34;False destination&#34; is a place that doesn't exist. Perhaps you tried to scry an enemy's sanctum but instead viewed an illusion, or you are attempting to teleport to a familiar location that no longer exists.</p>
					<p><b>On Target </b>. You and your group (or the target object) appear where you want to.</p>
					<p><b>Off Target </b>. You and your group (or the target object) appear a random distance away from the destination in a random direction. Distance off target is 1d10 &#215; 1d10 percent of the distance that was to be traveled. For example, if you tried to travel 120 miles, landed off target, and rolled a 5 and 3 on the two d10s, then you would be off target by 15 percent, or 18 miles. The GM determines the direction off target randomly by rolling a d8 and designating 1 as north, 2 as northeast, 3 as east, and so on around the points of the compass. If you were teleporting to a coastal city and wound up 18 miles out at sea, you could be in trouble.</p>
					<p><b>Similar Area </b>. You and your group (or the target object) wind up in a different area that's visually or thematically similar to the target area. If you are heading for your home laboratory, for example, you might wind up in another wizard's laboratory or in an alchemical supply shop that has many of the same tools and implements as your laboratory. Generally, you appear in the closest similar place, but since the spell has no range limit, you could conceivably wind up anywhere on the plane.</p>
					<p><b>Mishap </b>. The spell's unpredictable magic results in a difficult journey. Each teleporting creature (or the target object) takes 3d10 force damage, and the GM rerolls on the table to see where you wind up (multiple mishaps can occur, dealing damage each time).</p>
				</description>
				<duration type="string">Instantaneous</duration>
				<group type="string">ATT</group>
				<level type="number">7</level>
				<locked type="number">1</locked>
				<name type="string">Helm to Teleport</name>
				<prepared type="number">3</prepared>
				<range type="string">10 feet</range>
				<ritual type="number">0</ritual>
				<school type="string">Conjuration</school>
				<source type="string">Bard, Sorcerer, Wizard</source>
				<usesperiod type="string">once</usesperiod>
			</id-00008>
		</powers>
		<profbonus type="number">3</profbonus>
		<proficiencylist>
			<id-00001>
				<name type="string">Tool: Dice set, vehicles (land)</name>
			</id-00001>
			<id-00002>
				<name type="string">Weapon: Simple weapons, martial weapons</name>
			</id-00002>
			<id-00003>
				<name type="string">Armor: Light armor. medium armor, shields</name>
			</id-00003>
			<id-00004>
				<name type="string">Weapon: Improvised</name>
			</id-00004>
		</proficiencylist>
		<race type="string">Rock Gnome</race>
		<racelink type="windowreference">
			<class>reference_race</class>
			<recordname>reference.racedata.gnome@DD PHB Deluxe</recordname>
		</racelink>
		<senses type="string">Darkvision 60</senses>
		<size type="string">Small</size>
		<skilllist>
			<id-00001>
				<misc type="number">0</misc>
				<name type="string">Perception</name>
				<prof type="number">1</prof>
				<stat type="string">wisdom</stat>
				<total type="number">2</total>
			</id-00001>
			<id-00002>
				<misc type="number">0</misc>
				<name type="string">Athletics</name>
				<prof type="number">1</prof>
				<stat type="string">strength</stat>
				<total type="number">6</total>
			</id-00002>
			<id-00003>
				<misc type="number">0</misc>
				<name type="string">Intimidation</name>
				<prof type="number">1</prof>
				<stat type="string">charisma</stat>
				<total type="number">2</total>
			</id-00003>
			<id-00004>
				<misc type="number">0</misc>
				<name type="string">Arcana</name>
				<prof type="number">0</prof>
				<stat type="string">intelligence</stat>
				<total type="number">0</total>
			</id-00004>
			<id-00005>
				<misc type="number">0</misc>
				<name type="string">Persuasion</name>
				<prof type="number">0</prof>
				<stat type="string">charisma</stat>
				<total type="number">-1</total>
			</id-00005>
			<id-00006>
				<misc type="number">0</misc>
				<name type="string">Nature</name>
				<prof type="number">0</prof>
				<stat type="string">intelligence</stat>
				<total type="number">0</total>
			</id-00006>
			<id-00007>
				<misc type="number">0</misc>
				<name type="string">Medicine</name>
				<prof type="number">0</prof>
				<stat type="string">wisdom</stat>
				<total type="number">-1</total>
			</id-00007>
			<id-00008>
				<misc type="number">0</misc>
				<name type="string">Survival</name>
				<prof type="number">1</prof>
				<stat type="string">wisdom</stat>
				<total type="number">2</total>
			</id-00008>
			<id-00009>
				<misc type="number">0</misc>
				<name type="string">Performance</name>
				<prof type="number">0</prof>
				<stat type="string">charisma</stat>
				<total type="number">-1</total>
			</id-00009>
			<id-00010>
				<misc type="number">0</misc>
				<name type="string">Acrobatics</name>
				<prof type="number">0</prof>
				<stat type="string">dexterity</stat>
				<total type="number">2</total>
			</id-00010>
			<id-00011>
				<misc type="number">0</misc>
				<name type="string">Religion</name>
				<prof type="number">0</prof>
				<stat type="string">intelligence</stat>
				<total type="number">0</total>
			</id-00011>
			<id-00012>
				<misc type="number">0</misc>
				<name type="string">Sleight of Hand</name>
				<prof type="number">0</prof>
				<stat type="string">dexterity</stat>
				<total type="number">2</total>
			</id-00012>
			<id-00013>
				<misc type="number">0</misc>
				<name type="string">Insight</name>
				<prof type="number">0</prof>
				<stat type="string">wisdom</stat>
				<total type="number">-1</total>
			</id-00013>
			<id-00014>
				<misc type="number">0</misc>
				<name type="string">Deception</name>
				<prof type="number">0</prof>
				<stat type="string">charisma</stat>
				<total type="number">-1</total>
			</id-00014>
			<id-00015>
				<misc type="number">0</misc>
				<name type="string">Investigation</name>
				<prof type="number">0</prof>
				<stat type="string">intelligence</stat>
				<total type="number">0</total>
			</id-00015>
			<id-00016>
				<misc type="number">0</misc>
				<name type="string">Stealth</name>
				<prof type="number">0</prof>
				<stat type="string">dexterity</stat>
				<total type="number">2</total>
			</id-00016>
			<id-00017>
				<misc type="number">0</misc>
				<name type="string">History</name>
				<prof type="number">0</prof>
				<stat type="string">intelligence</stat>
				<total type="number">0</total>
			</id-00017>
			<id-00018>
				<misc type="number">0</misc>
				<name type="string">Animal Handling</name>
				<prof type="number">0</prof>
				<stat type="string">wisdom</stat>
				<total type="number">-1</total>
			</id-00018>
			<id-00019>
				<locked type="number">1</locked>
				<misc type="number">0</misc>
				<name type="string">Artificer's Lore(History)</name>
				<prof type="number">2</prof>
				<stat type="string">intelligence</stat>
				<total type="number">6</total>
			</id-00019>
		</skilllist>
		<speed>
			<armor type="number">0</armor>
			<base type="number">25</base>
			<misc type="number">10</misc>
			<temporary type="number">0</temporary>
			<total type="number">35</total>
		</speed>
		<temp>
		</temp>
		<token type="token">portrait_id-00008_token</token>
		<traitlist>
			<id-00001>
				<locked type="number">1</locked>
				<name type="string">Gnome Cunning</name>
				<source type="string">Gnome</source>
				<text type="formattedtext">
					<p>You have advantage on all Intelligence, Wisdom, and Charisma saving throws against magic.</p>
				</text>
				<type type="string">racial</type>
			</id-00001>
			<id-00002>
				<locked type="number">1</locked>
				<name type="string">Artificer's Lore</name>
				<source type="string">Rock Gnome</source>
				<text type="formattedtext">
					<p>Whenever you make an Intelligence (History) check related to magic items, alchemical objects, or technological devices, you can add twice your proficiency bonus, instead of any proficiency bonus you normally apply.</p>
				</text>
				<type type="string">subracial</type>
			</id-00002>
			<id-00003>
				<locked type="number">1</locked>
				<name type="string">Tinker</name>
				<source type="string">Rock Gnome</source>
				<text type="formattedtext">
					<p>You have proficiency with artisan's tools (tinker's tools). Using those tools, you can spend 1 hour and 10 gp worth of materials to construct a Tiny clockwork device (AC 5, 1 hp). The device ceases to function after 24 hours, or when you use your action to dismantle it; at that time, you can reclaim the materials used to create it. You can have up to three such devices active at a time.</p>
					<p>When you create a device, choose one of the following options.</p>
					<p>Clockwork Toy. This toy is a clockwork animal or person, such as a frog, mouse, bird, or soldier. When placed on the ground, the toy moves 5 feet across the ground on each of your turns in a random direction. It makes noises as appropriate to the creature it represents.</p>
					<p>Fire Starter. The device produces a miniature flame, which you can use to light a candle, torch, or campfire. Using the device requires your action.</p>
					<p>Music Box. When opened, this music box plays a single song at a moderate volume. The box stops playing when it reaches the song's end or when it is closed.</p>
				</text>
				<type type="string">subracial</type>
			</id-00003>
		</traitlist>
		<weapon>
			<critdicebonus>
			</critdicebonus>
			<critrange>
				<melee type="number">20</melee>
				<ranged type="number">20</ranged>
			</critrange>
		</weapon>
		<weaponlist>
			<id-00001>
				<carried type="number">2</carried>
				<damagelist>
					<id-00001>
						<dice type="dice">d8</dice>
						<stat type="string">base</stat>
						<type type="string">slashing</type>
					</id-00001>
				</damagelist>
				<isidentified type="number">1</isidentified>
				<maxammo type="number">0</maxammo>
				<name type="string">Battleaxe</name>
				<prof type="number">1</prof>
				<shortcut type="windowreference">
					<class>item</class>
					<recordname>....inventorylist.id-00009</recordname>
				</shortcut>
				<type type="number">0</type>
			</id-00001>
			<id-00002>
				<carried type="number">2</carried>
				<damagelist>
					<id-00001>
						<dice type="dice">d6</dice>
						<stat type="string">base</stat>
						<type type="string">piercing</type>
					</id-00001>
				</damagelist>
				<isidentified type="number">1</isidentified>
				<maxammo type="number">0</maxammo>
				<name type="string">Javelin</name>
				<prof type="number">1</prof>
				<shortcut type="windowreference">
					<class>item</class>
					<recordname>....inventorylist.id-00010</recordname>
				</shortcut>
				<type type="number">0</type>
			</id-00002>
			<id-00003>
				<ammo type="number">0</ammo>
				<carried type="number">2</carried>
				<damagelist>
					<id-00001>
						<dice type="dice">d6</dice>
						<stat type="string">base</stat>
						<statmult type="number">1</statmult>
						<type type="string">piercing</type>
					</id-00001>
				</damagelist>
				<isidentified type="number">1</isidentified>
				<maxammo type="number">3</maxammo>
				<name type="string">Javelin</name>
				<prof type="number">1</prof>
				<shortcut type="windowreference">
					<class>item</class>
					<recordname>....inventorylist.id-00010</recordname>
				</shortcut>
				<type type="number">2</type>
			</id-00003>
			<id-00004>
				<carried type="number">2</carried>
				<damagelist>
					<id-00001>
						<dice type="dice">d6</dice>
						<stat type="string">base</stat>
						<type type="string">slashing</type>
					</id-00001>
				</damagelist>
				<isidentified type="number">1</isidentified>
				<maxammo type="number">0</maxammo>
				<name type="string">Handaxe</name>
				<prof type="number">1</prof>
				<shortcut type="windowreference">
					<class>item</class>
					<recordname>....inventorylist.id-00011</recordname>
				</shortcut>
				<type type="number">0</type>
			</id-00004>
			<id-00005>
				<carried type="number">2</carried>
				<damagelist>
					<id-00001>
						<dice type="dice">d6</dice>
						<stat type="string">base</stat>
						<type type="string">slashing</type>
					</id-00001>
				</damagelist>
				<isidentified type="number">1</isidentified>
				<maxammo type="number">2</maxammo>
				<name type="string">Handaxe</name>
				<prof type="number">1</prof>
				<shortcut type="windowreference">
					<class>item</class>
					<recordname>....inventorylist.id-00011</recordname>
				</shortcut>
				<type type="number">2</type>
			</id-00005>
			<id-00007>
				<attackbonus type="number">0</attackbonus>
				<carried type="number">1</carried>
				<damagelist>
					<id-00001>
						<bonus type="number">0</bonus>
						<dice type="dice">d8</dice>
						<stat type="string">base</stat>
						<type type="string">necrotic,magic</type>
					</id-00001>
				</damagelist>
				<isidentified type="number">0</isidentified>
				<maxammo type="number">0</maxammo>
				<name type="string">** Boomerang of the Hidden Champion **</name>
				<prof type="number">1</prof>
				<properties type="string">Thrown (range 30/90), versatile (1d8)</properties>
				<shortcut type="windowreference">
					<class>item</class>
					<recordname>....inventorylist.id-00019</recordname>
				</shortcut>
				<type type="number">0</type>
			</id-00007>
			<id-00008>
				<attackbonus type="number">0</attackbonus>
				<carried type="number">1</carried>
				<damagelist>
					<id-00001>
						<bonus type="number">0</bonus>
						<dice type="dice">d8</dice>
						<stat type="string">base</stat>
						<type type="string">necrotic,magic</type>
					</id-00001>
				</damagelist>
				<isidentified type="number">0</isidentified>
				<maxammo type="number">1</maxammo>
				<name type="string">** Boomerang of the Hidden Champion **</name>
				<prof type="number">1</prof>
				<properties type="string">Thrown (range 30/90), versatile (1d8)</properties>
				<shortcut type="windowreference">
					<class>item</class>
					<recordname>....inventorylist.id-00019</recordname>
				</shortcut>
				<type type="number">2</type>
			</id-00008>
			<id-00009>
				<carried type="number">2</carried>
				<damagelist>
					<id-00001>
						<bonus type="number">0</bonus>
						<dice type="dice">d4</dice>
						<stat type="string">strength</stat>
						<statmult type="number">1</statmult>
						<type type="string">piercing</type>
					</id-00001>
				</damagelist>
				<maxammo type="number">0</maxammo>
				<name type="string">Bite</name>
				<prof type="number">1</prof>
				<shortcut type="windowreference">
					<class></class>
					<recordname></recordname>
				</shortcut>
				<type type="number">0</type>
			</id-00009>
		</weaponlist>
		<weight type="string">180lb</weight>
	</character>
</root>
